synthetic_panel/__init__.py
synthetic_panel/transitions.py
synthetic_panel-0.1.4.dist-info/licenses/LICENSE.txt
synthetic_panel-0.1.4.dist-info/METADATA
synthetic_panel-0.1.4.dist-info/WHEEL
synthetic_panel-0.1.4.dist-info/top_level.txt
synthetic_panel-0.1.4.dist-info/RECORD
